ukat/__init__.py
ukat/data/__init__.py
ukat/data/fetch.py
ukat/data/tests/__init__.py
ukat/data/tests/test_fetch.py
ukat/mapping/__init__.py
ukat/mapping/b0.py
ukat/mapping/diffusion.py
ukat/mapping/mtr.py
ukat/mapping/t1.py
ukat/mapping/t2.py
ukat/mapping/t2_stimfit.py
ukat/mapping/t2star.py
ukat/mapping/fitting/__init__.py
ukat/mapping/fitting/relaxation.py
ukat/mapping/fitting/tests/__init__.py
ukat/mapping/fitting/tests/test_relaxation.py
ukat/mapping/resources/__init__.py
ukat/mapping/resources/t2_stimfit/__init__.py
ukat/mapping/resources/t2_stimfit/rf_pulses.py
ukat/mapping/tests/__init__.py
ukat/mapping/tests/test_b0.py
ukat/mapping/tests/test_diffusion.py
ukat/mapping/tests/test_mtr.py
ukat/mapping/tests/test_t1.py
ukat/mapping/tests/test_t2.py
ukat/mapping/tests/test_t2_stimfit.py
ukat/mapping/tests/test_t2star.py
ukat/qa/__init__.py
ukat/qa/snr.py
ukat/qa/tests/__init__.py
ukat/qa/tests/test_snr.py
ukat/segmentation/__init__.py
ukat/segmentation/whole_kidney.py
ukat/segmentation/tests/__init__.py
ukat/segmentation/tests/test_whole_kidney.py
ukat/utils/__init__.py
ukat/utils/arraystats.py
ukat/utils/ge.py
ukat/utils/siemens.py
ukat/utils/tools.py
ukat/utils/tests/__init__.py
ukat/utils/tests/test_arraystats.py
ukat/utils/tests/test_ge.py
ukat/utils/tests/test_siemens.py
ukat/utils/tests/test_tools.py
ukat/utils/tests/test_data/diffusion_scheme.txt
ukat/utils/tests/test_data/expected_from_str.dvs
ukat/utils/tests/test_data/expected_from_txt.dvs
ukat/vessels/__init__.py
ukat/vessels/phase_contrast.py
ukat/vessels/tests/__init__.py
ukat/vessels/tests/test_phase_contrast.py
ukat-0.7.3.dist-info/LICENSE
ukat-0.7.3.dist-info/METADATA
ukat-0.7.3.dist-info/WHEEL
ukat-0.7.3.dist-info/top_level.txt
ukat-0.7.3.dist-info/RECORD
