Metadata-Version: 2.1
Name: ukat
Version: 0.7.3
Summary: UKRIN Kidney Analysis Toolbox
Home-page: https://github.com/UKRIN-MAPS/ukat
License: GPL-3.0
Platform: UNKNOWN
Classifier: Development Status :: 4 - Beta
Classifier: Intended Audience :: Developers
Classifier: Intended Audience :: Science/Research
Classifier: Topic :: Scientific/Engineering
Classifier: Environment :: Console
Classifier: Operating System :: OS Independent
Classifier: Programming Language :: Python :: 3.8
Classifier: Programming Language :: Python :: 3.9
Classifier: Programming Language :: Python :: 3.10
Classifier: Programming Language :: Python :: 3.11
Classifier: License :: OSI Approved :: GNU General Public License v3 (GPLv3)
Requires-Python: >=3.8, <4
Requires-Dist: dipy>=1.6.0
Requires-Dist: matplotlib>=3.7.0
Requires-Dist: nibabel>=5.0.1
Requires-Dist: notebook>=6.5.1
Requires-Dist: numba>=0.55.1
Requires-Dist: numpy>=1.24.1
Requires-Dist: pandas>=2.0.0
Requires-Dist: pathos>=0.3.0
Requires-Dist: renalsegmentor>=1.3.5
Requires-Dist: scikit-image<0.22,>=0.20.0
Requires-Dist: scipy<1.12,>=1.9.1
Requires-Dist: scikit-learn~=1.2.1
Requires-Dist: tabulate>=0.9.0
Requires-Dist: tqdm>=4.64.1
